a_pandas_ex_vertical_to_horizontal/README.MD
a_pandas_ex_vertical_to_horizontal/__init__.py
a_pandas_ex_vertical_to_horizontal/requirements.txt
a_pandas_ex_vertical_to_horizontal/thirdparty.json
a_pandas_ex_vertical_to_horizontal-0.10.dist-info/LICENSE.rst
a_pandas_ex_vertical_to_horizontal-0.10.dist-info/METADATA
a_pandas_ex_vertical_to_horizontal-0.10.dist-info/WHEEL
a_pandas_ex_vertical_to_horizontal-0.10.dist-info/top_level.txt
a_pandas_ex_vertical_to_horizontal-0.10.dist-info/RECORD
